{
  "pages": [
    //pages数组中第一项表示应用启动页，参考：https://uniapp.dcloud.io/collocation/pages
    {
      "path": "pages/inner-components/index",
      "style": {
        "navigationBarTitleText": "内置组件"
      }
    },
    {
      "path": "pages/index/index",
      "style": {
        "navigationBarTitleText": "uni-app-home"
      }
    },
    {
      "path": "pages/extra-components/index",
      "style": {
        "navigationBarTitleText": "扩展组件"
      }
    },
    {
      "path": "pages/api/index",
      "style": {
        "navigationBarTitleText": "API能力"
      }
    },
    {
      "path": "pages/biz-demo/index",
      "style": {
        "navigationBarTitleText": "业务相关"
      }
    },
    {
      "path": "pages/axios/index",
      "style": {
        "navigationBarTitleText": "Axios（网络请求示例）"
      }
    },
    {
      "path": "pages/uview/index",
      "style": {
        "navigationBarTitleText": "uView 示例组件"
      }
    },
    {
      "path": "pages/webview/index",
      "style": {
        "navigationBarTitleText": "webview示例"
      }
    },
    {
      "path": "pages/platformAbility/index",
      "style": {
        "navigationBarTitleText": "跨平台能力展示"
      }
    },
    {
      "path": "pages/smashEgg/index",
      "style": {
        "navigationBarTitleText": "砸金蛋"
      }
    },
    {
      "path": "pages/login/index",
      "style": {
        "navigationBarTitleText": "登录"
      }
    },
    {
      "path": "pages/component/view/view",
      "style": {
        "navigationBarTitleText": "view"
      }
    },
    {
      "path": "pages/component/scroll-view/scroll-view",
      "style": {
        "navigationBarTitleText": "scroll-view"
      }
    },
    {
      "path": "pages/component/swiper/swiper",
      "style": {
        "navigationBarTitleText": "swiper"
      }
    },
    {
      "path": "pages/component/movable-view/movable-view",
      "style": {
        "navigationBarTitleText": "movable-view"
      }
    },
    {
      "path": "pages/component/cover-view/cover-view",
      "style": {
        "navigationBarTitleText": "cover-view"
      }
    },
    {
      "path": "pages/component/text/text",
      "style": {
        "navigationBarTitleText": "text"
      }
    },
    {
      "path": "pages/component/rich-text/rich-text",
      "style": {
        "navigationBarTitleText": "rich-text"
      }
    },
    {
      "path": "pages/component/progress/progress",
      "style": {
        "navigationBarTitleText": "progress"
      }
    },
    {
      "path": "pages/component/button/button",
      "style": {
        "navigationBarTitleText": "button"
      }
    },
    {
      "path": "pages/component/checkbox/checkbox",
      "style": {
        "navigationBarTitleText": "checkbox"
      }
    },
    {
      "path": "pages/component/form/form",
      "style": {
        "navigationBarTitleText": "form"
      }
    },
    {
      "path": "pages/component/input/input",
      "style": {
        "navigationBarTitleText": "input"
      }
    },
    {
      "path": "pages/component/label/label",
      "style": {
        "navigationBarTitleText": "label"
      }
    },
    {
      "path": "pages/component/picker/picker",
      "style": {
        "navigationBarTitleText": "picker"
      }
    },
    {
      "path": "pages/component/picker-view/picker-view",
      "style": {
        "navigationBarTitleText": "picker-view"
      }
    },
    {
      "path": "pages/component/radio/radio",
      "style": {
        "navigationBarTitleText": "radio"
      }
    },
    {
      "path": "pages/component/slider/slider",
      "style": {
        "navigationBarTitleText": "slider"
      }
    },
    {
      "path": "pages/component/switch/switch",
      "style": {
        "navigationBarTitleText": "switch"
      }
    },
    {
      "path": "pages/component/textarea/textarea",
      "style": {
        "navigationBarTitleText": "textarea"
      }
    },
    {
      "path": "pages/component/navigator/navigator",
      "style": {
        "navigationBarTitleText": "navigator"
      }
    },
    {
      "path": "pages/component/navigator/navigate/navigate",
      "style": {
        "navigationBarTitleText": "navigatePage"
      }
    },
    {
      "path": "pages/component/navigator/redirect/redirect",
      "style": {
        "navigationBarTitleText": "redirectPage"
      }
    },
    {
      "path": "pages/component/image/image",
      "style": {
        "navigationBarTitleText": "image"
      }
    },
    {
      "path": "pages/component/video/video",
      "style": {
        "navigationBarTitleText": "video"
      }
    },
    {
      "path": "pages/component/map/map",
      "style": {
        "navigationBarTitleText": "map"
      }
    },
    {
      "path": "pages/component/canvas/canvas",
      "style": {
        "navigationBarTitleText": "canvas"
      }
    },
    {
      "path": "pages/component/web-view/web-view",
      "style": {
        "navigationBarTitleText": "web-view"
      }
    },
    {
      "path": "pages/extUI/badge/badge",
      "style": {
        "navigationBarTitleText": "badge"
      }
    },
    {
      "path": "pages/extUI/breadcrumb/breadcrumb",
      "style": {
        "navigationBarTitleText": "breadcrumb"
      }
    },
    {
      "path": "pages/extUI/card/card",
      "style": {
        "navigationBarTitleText": "card"
      }
    },
    {
      "path": "pages/extUI/collapse/collapse",
      "style": {
        "navigationBarTitleText": "collapse"
      }
    },
    {
      "path": "pages/extUI/combox/combox",
      "style": {
        "navigationBarTitleText": "combox"
      }
    },
    {
      "path": "pages/extUI/countdown/countdown",
      "style": {
        "navigationBarTitleText": "countdown"
      }
    },
    {
      "path": "pages/extUI/data-checkbox/data-checkbox",
      "style": {
        "navigationBarTitleText": "data-checkbox"
      }
    },
    {
      "path": "pages/extUI/data-picker/data-picker",
      "style": {
        "navigationBarTitleText": "data-picker"
      }
    },
    {
      "path": "pages/extUI/data-select/data-select",
      "style": {
        "navigationBarTitleText": "data-select"
      }
    },
    {
      "path": "pages/extUI/dateformat/dateformat",
      "style": {
        "navigationBarTitleText": "dateformat"
      }
    },
    {
      "path": "pages/extUI/datetime-picker/datetime-picker",
      "style": {
        "navigationBarTitleText": "datetime-picker"
      }
    },
    {
      "path": "pages/extUI/drawer/drawer",
      "style": {
        "navigationBarTitleText": "drawer"
      }
    },
    {
      "path": "pages/extUI/easyinput/easyinput",
      "style": {
        "navigationBarTitleText": "easyinput"
      }
    },
    {
      "path": "pages/extUI/fab/fab",
      "style": {
        "navigationBarTitleText": "fab"
      }
    },
    {
      "path": "pages/extUI/fav/fav",
      "style": {
        "navigationBarTitleText": "fav"
      }
    },
    {
      "path": "pages/extUI/file-picker/file-picker",
      "style": {
        "navigationBarTitleText": "file-picker"
      }
    },
    {
      "path": "pages/extUI/forms/forms",
      "style": {
        "navigationBarTitleText": "forms"
      }
    },
    {
      "path": "pages/extUI/goods-nav/goods-nav",
      "style": {
        "navigationBarTitleText": "goods-nav"
      }
    },
    {
      "path": "pages/extUI/grid/grid",
      "style": {
        "navigationBarTitleText": "grid"
      }
    },
    {
      "path": "pages/extUI/group/group",
      "style": {
        "navigationBarTitleText": "group"
      }
    },
    {
      "path": "pages/extUI/icons/icons",
      "style": {
        "navigationBarTitleText": "icons"
      }
    },
    {
      "path": "pages/extUI/indexed-list/indexed-list",
      "style": {
        "navigationBarTitleText": "indexed-list"
      }
    },
    {
      "path": "pages/extUI/link/link",
      "style": {
        "navigationBarTitleText": "link"
      }
    },
    {
      "path": "pages/extUI/list/list",
      "style": {
        "navigationBarTitleText": "list"
      }
    },
    {
      "path": "pages/extUI/load-more/load-more",
      "style": {
        "navigationBarTitleText": "load-more"
      }
    },
    {
      "path": "pages/extUI/nav-bar/nav-bar",
      "style": {
        "navigationBarTitleText": "nav-bar"
      }
    },
    {
      "path": "pages/extUI/notice-bar/notice-bar",
      "style": {
        "navigationBarTitleText": "notice-bar"
      }
    },
    {
      "path": "pages/extUI/number-box/number-box",
      "style": {
        "navigationBarTitleText": "number-box"
      }
    },
    {
      "path": "pages/extUI/pagination/pagination",
      "style": {
        "navigationBarTitleText": "pagination"
      }
    },
    {
      "path": "pages/extUI/popup/popup",
      "style": {
        "navigationBarTitleText": "popup"
      }
    },
    {
      "path": "pages/extUI/rate/rate",
      "style": {
        "navigationBarTitleText": "rate"
      }
    },
    {
      "path": "pages/extUI/row/row",
      "style": {
        "navigationBarTitleText": "row"
      }
    },
    {
      "path": "pages/extUI/search-bar/search-bar",
      "style": {
        "navigationBarTitleText": "search-bar"
      }
    },
    {
      "path": "pages/extUI/section/section",
      "style": {
        "navigationBarTitleText": "section"
      }
    },
    {
      "path": "pages/extUI/segmented-control/segmented-control",
      "style": {
        "navigationBarTitleText": "segmented-control"
      }
    },
    {
      "path": "pages/extUI/steps/steps",
      "style": {
        "navigationBarTitleText": "steps"
      }
    },
    {
      "path": "pages/extUI/swipe-action/swipe-action",
      "style": {
        "navigationBarTitleText": "swipe-action"
      }
    },
    {
      "path": "pages/extUI/swiper-dot/swiper-dot",
      "style": {
        "navigationBarTitleText": "swiper-dot"
      }
    },
    {
      "path": "pages/extUI/table/table",
      "style": {
        "navigationBarTitleText": "table"
      }
    },
    {
      "path": "pages/extUI/tag/tag",
      "style": {
        "navigationBarTitleText": "tag"
      }
    },
    {
      "path": "pages/extUI/title/title",
      "style": {
        "navigationBarTitleText": "title"
      }
    },
    {
      "path": "pages/extUI/tooltip/tooltip",
      "style": {
        "navigationBarTitleText": "tooltip"
      }
    },
    {
      "path": "pages/extUI/transition/transition",
      "style": {
        "navigationBarTitleText": "transition"
      }
    }
  ],
  "tabBar": {
    "color": "#7A7E83",
    "selectedColor": "#3B7CF7",
    "borderStyle": "black",
    "backgroundColor": "#ffffff",
    "list": [
      {
        "pagePath": "pages/inner-components/index",
        "iconPath": "/static/component.png",
        "selectedIconPath": "/static/componentHL.png",
        "text": "内置组件"
      },
      {
        "pagePath": "pages/api/index",
        "iconPath": "/static/api.png",
        "selectedIconPath": "/static/apiHL.png",
        "text": "API能力"
      },
      {
        "pagePath": "pages/extra-components/index",
        "iconPath": "/static/component.png",
        "selectedIconPath": "/static/componentHL.png",
        "text": "扩展组件"
      },
      {
        "pagePath": "pages/biz-demo/index",
        "iconPath": "/static/template.png",
        "selectedIconPath": "/static/templateHL.png",
        "text": "业务"
      }
    ]
  },
  "globalStyle": {
    "navigationBarTextStyle": "black",
    "navigationBarTitleText": "uni-app",
    "navigationBarBackgroundColor": "#F8F8F8",
    "backgroundColor": "#F8F8F8"
  },
  "easycom": {
    "custom": {
      // uni-ui 规则如下配置
      "^uni-(.*)": "@dcloudio/uni-ui/lib/uni-$1/uni-$1.vue"
    }
  }
}
